cdfs/__init__.py
cdfs/arrays/__init__.py
cdfs/arrays/timecontentsproxy.py
cdfs/basecdfs.py
cdfs/components/__init__.py
cdfs/components/basecdfscomponent.py
cdfs/components/basetablecdfscomponent.py
cdfs/components/metainformationcdfscomponent.py
cdfs/components/timecontentscdfscomponent.py
cdfs/contentsfile.py
cdfs/header.py
cdfs/py.typed
cdfs/tables/__init__.py
cdfs/tables/basecontentstable.py
cdfs/tables/basemetainformationtable.py
cdfs/tables/basetable.py
cdfs/tables/basetimecontentstable.py
cdfs-0.3.0.dist-info/LICENSE.rst
cdfs-0.3.0.dist-info/METADATA
cdfs-0.3.0.dist-info/WHEEL
cdfs-0.3.0.dist-info/entry_points.txt
cdfs-0.3.0.dist-info/RECORD
