Metadata-Version: 2.1
Name: cdfs
Version: 0.3.0
Summary: Continous Data File System
Home-page: https://github.com/fongant/python-cdfs
License: MIT
Author: Anthony Fong
Author-email: FongAnthonyM@gmail.com
Requires-Python: >=3.10,<4.0
Classifier: Development Status :: 1 - Planning
Classifier: License :: OSI Approved :: MIT License
Classifier: Programming Language :: Python :: 3
Classifier: Programming Language :: Python :: 3.10
Classifier: Programming Language :: Python :: 3.11
Requires-Dist: SQLAlchemy (>=2.0.19)
Requires-Dist: aiosqlite (>=0.19.0)
Requires-Dist: baseobjects (>=1.11.0)
Requires-Dist: click (>=8.0.3)
Requires-Dist: dspobjects (>=0.4.0)
Requires-Dist: h5py (>=3.8.0)
Requires-Dist: hdf5objects (>=0.5.0)
Requires-Dist: numpy (>=1.24.3)
Requires-Dist: proxyarrays (>=0.6.0)
Project-URL: Changelog, https://github.com/fongant/python-cdfs/releases
Project-URL: Documentation, https://python-cdfs.readthedocs.io
Project-URL: Repository, https://github.com/fongant/python-cdfs
